{
  "BOSS_RELIC": "ボスレリックと交換",
  "THREE_CARDS": "レアカード3枚から1枚を選択",
  "THREE_SMALL_POTIONS": "ポーションを3つ獲得",
  "RANDOM_COLORLESS": "無色カードをランダムに1枚獲得",
  "REMOVE_CARD": "カードを1枚除去",
  "TRANSFORM_CARD": "カードを1枚変化",
  "UPGRADE_CARD": "カードを1枚アップグレード",
  "TEN_PERCENT_HP_BONUS": "最大HPが10%増加",
  "TWENTY_PERCENT_HP_BONUS": "最大HPが20%増加",
  "THREE_ENEMY_KILL": "最初の3戦闘で敵のHPが1になる",
  "HUNDRED_GOLD": "100ゴールド獲得",
  "RANDOM_COLORLESS_2": "無色カードをランダムに2枚獲得",
  "THREE_RARE_CARDS": "レアカード3枚から1枚を選んで獲得",
  "MAX_HP_FOR_CARD": "最大HPを減少する代わりにレアカードを獲得",
  "CURSE_FOR_GOLD": "呪いカードを受け取る代わりにゴールドを獲得",
  "TRANSFORM_TWO_CARDS": "カードを2枚変化",
  "REMOVE_TWO": "カードを2枚除去",
  "ONE_RANDOM_RARE_CARD": "ランダムなレアカードを1枚獲得",
  "RANDOM_COMMON_RELIC": "ランダムな通常レリックを獲得",
  "TWO_FIFTY_GOLD": "250ゴールド獲得",
  "TRANSFORM_AND_UPGRADE_CARD": "カードを1枚変化してアップグレード",
  "TWENTY_PERCENT_HP_LOSS": "最大HPが20%減少",
  "TEN_PERCENT_HP_LOSS": "最大HPが10%減少",
  "RANDOM_RARE_RELIC": "ランダムなレアレリックを獲得",
  "TWO_RANDOM_RARE_CARDS": "ランダムなレアカードを2枚獲得",
  "ONE_RARE_RELIC": "レアレリックを1個獲得",
  "neowBonus": "ネオーの祝福",
  "totalSelected": "選択回数（通算）",
  "last50Selected": "選択回数（直近50戦）",
  "totalWinRate": "勝率（通算）",
  "last50WinRate": "勝率（直近50戦）",
  "neowBonus": {
    "THREE_CARDS": "カードを3枚選択",
    "ONE_RANDOM_RARE_CARD": "レアカードをランダムに1枚獲得",
    "REMOVE_CARD": "カードを1枚除去",
    "UPGRADE_CARD": "カードを1枚アップグレード",
    "RANDOM_COLORLESS": "無色のカードをランダムに1枚獲得",
    "THREE_SMALL_POTIONS": "小さいポーションを3個獲得",
    "RANDOM_COMMON_RELIC": "コモンレリックをランダムに1個獲得",
    "TEN_PERCENT_HP_BONUS": "最大HPが10%増加",
    "THREE_ENEMY_KILL": "次の3戦闘で敵が1HPで開始",
    "HUNDRED_GOLD": "100ゴールドを獲得",
    "REMOVE_TWO": "カードを2枚除去",

    "THREE_RARE_CARDS": "レアカードを3枚選択",
    "TWO_FIFTY_GOLD": "250ゴールドを獲得",
    "TRANSFORM_TWO_CARDS": "カードを2枚変化",
    "TWENTY_PERCENT_HP_BONUS": "最大HPが20%増加",
    "BOSS_RELIC": "ボスレリックを交換",
    "TRANSFORM_TWO_CARDS_UPGRADED": "カードを2枚変化（アップグレード）"
  }
} 